delegator.py
delegator.py-0.1.0.dist-info/DESCRIPTION.rst
delegator.py-0.1.0.dist-info/METADATA
delegator.py-0.1.0.dist-info/RECORD
delegator.py-0.1.0.dist-info/WHEEL
delegator.py-0.1.0.dist-info/metadata.json
delegator.py-0.1.0.dist-info/top_level.txt
