Metadata-Version: 1.1
Name: delegator.py
Version: 0.1.0
Summary: Subprocesses for Humans 2.0.
Home-page: https://github.com/kennethreitz/delegator
Author: Kenneth Reitz
Author-email: me@kennethreitz.com
License: MIT
Platform: UNKNOWN
Classifier: Programming Language :: Python
Classifier: Programming Language :: Python :: 2.6
Classifier: Programming Language :: Python :: 2.7
Classifier: Programming Language :: Python :: 3
Classifier: Programming Language :: Python :: 3.3
Classifier: Programming Language :: Python :: 3.4
Classifier: Programming Language :: Python :: 3.5
Classifier: Programming Language :: Python :: 3.6
Classifier: Programming Language :: Python :: Implementation :: CPython
Classifier: Programming Language :: Python :: Implementation :: PyPy
